{
  "header.top.tagline": "Für die Natur, für die Zukunft",
  "header.top.contact_us": "Kontakt",

  "header.top.github.aria": "GitHub-Repository öffnen",
  "header.top.github.cta": "Mach den Unterschied",

  "header.top.languages_menu_aria": "Sprache auswählen",
  "header.top.languages.pt": "Portugiesisch",
  "header.top.languages.en": "Englisch",
  "header.top.languages.es": "Spanisch",
  "header.top.languages.fr": "Französisch",
  "header.top.languages.de": "Deutsch",

  "header.top.social_titles.facebook": "Facebook",
  "header.top.social_titles.twitter": "Twitter",
  "header.top.social_titles.instagram": "Instagram",

  "header.top.links.about": "Über uns",
  "header.top.links.circular_partnerships": "Kreislaufpartnerschaften",
  "header.top.links.blog": "Blog",
  "header.top.links.contact": "Kontakt",
  "header.top.links.faq": "FAQ",
  "header.top.links.newsletter": "Newsletter",

  "header.logo_alt": "P7CO™ EcoResupply",

  "header.search.placeholder": "Suchen…",
  "header.search.aria": "Website durchsuchen",
  "header.search.input_aria": "Suchbegriff",
  "header.search.submit": "Suchen",

  "header.messages.label": "# Nachr ",
  "header.messages.aria_icon": "Nachrichten",
  "header.messages.icon_alt": "Nachrichten",
  "header.messages.loading": "Wird geladen…",
  "header.messages.view_all": "Alle anzeigen",
  "header.messages.empty": "Keine neuen Nachrichten",
  "header.messages.error": "Laden nicht möglich.",
  "header.messages.new": "Neu",
  "header.messages.open": "Öffnen",

  "header.nav.toggle": "Navigation umschalten",

  "header.nav.home.label": "Startseite",
  "header.nav.home.cta_panel.badge": "GITHUB",
  "header.nav.home.cta_panel.title": "MITWIRKEN",
  "header.nav.home.cta_panel.description": "Artikel, Übersetzungen, Veröffentlichungen.",
  "header.nav.home.cta_panel.button": "REPOSITORY",
  "header.nav.home.cta_panel.aria": "Repository öffnen",
  "header.nav.home.about.title": "ÜBER DAS PROJEKT",
  "header.nav.home.about.items.about_us": "Über uns",
  "header.nav.home.about.items.how_it_works": "Wie es funktioniert",
  "header.nav.home.about.items.mission_vision": "Mission & Vision",
  "header.nav.home.about.items.circular_partnerships": "Kreislaufpartnerschaften",
  "header.nav.home.about.items.mobile_app": "Mobile App",
  "header.nav.home.get_started.title": "STARTEN",
  "header.nav.home.get_started.items.create_account": "Konto erstellen",
  "header.nav.home.get_started.items.quick_guides": "Schnellstartanleitungen ansehen",
  "header.nav.home.resources.title": "RESSOURCEN",
  "header.nav.home.resources.items.circular_map": "Kreislaufkarte",
  "header.nav.home.resources.items.licensed_operators": "Lizenzierte Betreiber",
  "header.nav.home.resources.items.environmental_reports": "Umweltmeldungen",
  "header.nav.home.resources.items.fires_map": "Karte der Brände (PT)",
  "header.nav.home.resources.items.indicators_data": "Indikatoren & Daten",
  "header.nav.home.community.title": "GEMEINSCHAFT",
  "header.nav.home.community.items.blog": "Blog",
  "header.nav.home.community.items.translations": "Übersetzungen",
  "header.nav.home.community.items.contribute": "Beitragen",

  "header.nav.taxonomy.label": "Veränderung",
  "header.nav.taxonomy.circularity.title": "KREISLAUFWIRTSCHAFT",
  "header.nav.taxonomy.circularity.items.available_surpluses": "Verfügbare Überschüsse",
  "header.nav.taxonomy.circularity.items.reuse_cases": "Wiederverwendungsfälle",
  "header.nav.taxonomy.circularity.items.featured_materials": "Hervorgehobene Materialien",
  "header.nav.taxonomy.circularity.items.impact_indicators": "Auswirkungsindikatoren",
  "header.nav.taxonomy.reports.title": "MELDUNGEN",
  "header.nav.taxonomy.reports.items.reports_map": "Meldungskarte",
  "header.nav.taxonomy.reports.items.categories": "Kategorien",
  "header.nav.taxonomy.reports.items.official_guidelines": "Amtliche Leitlinien",
  "header.nav.taxonomy.reports.items.regional_stats": "Regionale Statistiken",
  "header.nav.taxonomy.esg.title": "ESG & UNTERNEHMEN",
  "header.nav.taxonomy.esg.items.mirr_reports": "MIRR-Berichte",
  "header.nav.taxonomy.esg.items.green_certs": "Grüne Zertifizierungen",
  "header.nav.taxonomy.esg.items.success_cases": "Erfolgsgeschichten",
  "header.nav.taxonomy.esg.items.circular_partnerships": "Kreislaufpartnerschaften",
  "header.nav.taxonomy.cta_block.badge": "STARTEN",
  "header.nav.taxonomy.cta_block.title": "JETZT",
  "header.nav.taxonomy.cta_block.description": "Erkunden, melden, teilen und wiederverwenden.",
  "header.nav.taxonomy.cta_block.button": "MITMACHEN",
  "header.nav.taxonomy.cta_block.alt": "P7CO CTA",

  "header.nav.blog.label": "Blog",
  "header.nav.blog.explore.title": "Entdecken",
  "header.nav.blog.explore.items.all_posts": "Alle Artikel",
  "header.nav.blog.explore.items.featured": "Hervorgehoben",
  "header.nav.blog.explore.items.most_read": "Meistgelesen",
  "header.nav.blog.explore.items.authors": "Autoren",
  "header.nav.blog.categories.title": "Kategorien",
  "header.nav.blog.categories.items.guides": "Leitfäden",
  "header.nav.blog.categories.items.news": "Nachrichten",
  "header.nav.blog.categories.items.case_studies": "Fallstudien",
  "header.nav.blog.categories.items.esg": "ESG",
  "header.nav.blog.categories.items.tech": "Technologie",
  "header.nav.blog.languages.title": "Sprachen",
  "header.nav.blog.languages.items.pt": "Portugiesisch",
  "header.nav.blog.languages.items.en": "Englisch",
  "header.nav.blog.languages.items.es": "Spanisch",
  "header.nav.blog.languages.items.fr": "Französisch",
  "header.nav.blog.languages.items.de": "Deutsch",

  "header.nav.pages.label": "Über uns",
  "header.nav.pages.about.title": "Über",
  "header.nav.pages.about.items.about_us": "Über uns",
  "header.nav.pages.about.items.team": "Team",
  "header.nav.pages.about.items.careers": "Karriere",
  "header.nav.pages.contacts.title": "Kontakt",
  "header.nav.pages.contacts.items.contacts": "Kontakte",
  "header.nav.pages.contacts.items.support": "Support",
  "header.nav.pages.faq.title": "FAQ",
  "header.nav.pages.faq.items.general_faq": "Allgemeine FAQ",
  "header.nav.pages.faq.items.terms": "Nutzungsbedingungen",
  "header.nav.pages.faq.items.privacy": "Datenschutzrichtlinie",
  "header.nav.pages.faq.items.cookies": "Cookies",
  "header.nav.pages.faq.items.acknowledgements": "Danksagungen",

  "header.nav.right.complaints": "Umweltmeldungen",
  "header.nav.right.surpluses": "Überschüsse",

  "header.auth.guest_menu_label": "Anmelden",
  "header.auth.login": "Login",
  "header.auth.login_aria": "Anmelden",
  "header.auth.create_account": "Konto erstellen",
  "header.auth.user_menu_label": "Hallo, {name}",
  "header.auth.dashboard": "Dashboard",
  "header.auth.my_listings": "Meine Einträge",
  "header.auth.settings": "Einstellungen",
  "header.auth.logout": "Abmelden",
  "header.auth.profile": "Profil ansehen",
  "header.auth.change_password": "Passwort ändern",
  "header.auth.account_menu_aria": "Konto",
  "header.auth.account_fallback": "Konto",

  "header.cta_primary.text": "STARTEN",
  "header.cta_primary.icon": "fa-seedling",

  "header.nav.in.label": "Indikatoren",
  "header.nav.in.explore.items.gee": "Treibhausgas emissionen (PT)",
  "header.nav.in.categories.items.c27a": "KreislaufwirtschaftEU27 (aktuelles jahr)",
  "header.nav.in.categories.items.c27": "KreislaufwirtschaftEU27 (technische ansicht)"
}
