{
  "kicker": "A ESCOLHA CERTA",
  "rotator": ["inova.", "transforma.", "conquista."],
  "lead1": "Com o P7CO® RESUPPLY, tornamos a economia circular acessível e simples. O nosso objetivo é ligar empresas, promover práticas sustentáveis e reduzir o desperdício de recursos.",
  "lead2": "A nossa missão é colaborar com empresas para fomentar a reutilização e promover a sustentabilidade em várias indústrias. Estamos aqui para criar um futuro mais verde e inovador, baseado em soluções circulares.",
  "cta": { "more_about": "Saiba Mais Sobre Nós" },
  "image": { "alt": "Parcerias P7CO® — empresas e sustentabilidade" }
}
