{
  "header.top.tagline": "Por la naturaleza, por el futuro",
  "header.top.contact_us": "Contactos",

  "header.top.github.aria": "Abrir repositorio de GitHub",
  "header.top.github.cta": "Contribuir — marca la diferencia",

  "header.top.languages_menu_aria": "Seleccionar idioma",
  "header.top.languages.pt": "Portugués",
  "header.top.languages.en": "Inglés",
  "header.top.languages.es": "Español",
  "header.top.languages.fr": "Francés",
  "header.top.languages.de": "Alemán",

  "header.top.social_titles.facebook": "Facebook",
  "header.top.social_titles.twitter": "Twitter",
  "header.top.social_titles.instagram": "Instagram",

  "header.top.links.about": "Acerca de",
  "header.top.links.circular_partnerships": "Alianzas Circulares",
  "header.top.links.blog": "Blog",
  "header.top.links.contact": "Contacto",
  "header.top.links.faq": "FAQ",
  "header.top.links.newsletter": "Boletín",

  "header.logo_alt": "P7CO™ EcoResupply",

  "header.search.placeholder": "Buscar…",
  "header.search.aria": "Buscar en el sitio",
  "header.search.input_aria": "Término de búsqueda",
  "header.search.submit": "Buscar",

  "header.messages.label": "# Mens. ",
  "header.messages.aria_icon": "Mensajes",
  "header.messages.icon_alt": "Mensajes",
  "header.messages.loading": "Cargando…",
  "header.messages.view_all": "Ver todos",
  "header.messages.empty": "No hay mensajes nuevos",
  "header.messages.error": "No se pudo cargar.",
  "header.messages.new": "Nuevo",
  "header.messages.open": "Abrir",

  "header.nav.toggle": "Alternar navegación",

  "header.nav.home.label": "Inicio",
  "header.nav.home.cta_panel.badge": "GITHUB",
  "header.nav.home.cta_panel.title": "CONTRIBUIR",
  "header.nav.home.cta_panel.description": "Artículos, traducciones, publicaciones.",
  "header.nav.home.cta_panel.button": "REPOSITORIO",
  "header.nav.home.cta_panel.aria": "Abrir repositorio",
  "header.nav.home.about.title": "SOBRE EL PROYECTO",
  "header.nav.home.about.items.about_us": "Acerca de nosotros",
  "header.nav.home.about.items.how_it_works": "Cómo funciona",
  "header.nav.home.about.items.mission_vision": "Misión & Visión",
  "header.nav.home.about.items.circular_partnerships": "Alianzas Circulares",
  "header.nav.home.about.items.mobile_app": "Aplicación Móvil",
  "header.nav.home.get_started.title": "EMPEZAR",
  "header.nav.home.get_started.items.create_account": "Crear cuenta",
  "header.nav.home.get_started.items.quick_guides": "Ver guías rápidas",
  "header.nav.home.resources.title": "RECURSOS",
  "header.nav.home.resources.items.circular_map": "Mapa de Circularidad",
  "header.nav.home.resources.items.licensed_operators": "Operadores Licenciados",
  "header.nav.home.resources.items.environmental_reports": "Denuncias Ambientales",
  "header.nav.home.resources.items.fires_map": "Mapa de Incendios (PT)",
  "header.nav.home.resources.items.indicators_data": "Indicadores & Datos",
  "header.nav.home.community.title": "COMUNIDAD",
  "header.nav.home.community.items.blog": "Blog",
  "header.nav.home.community.items.translations": "Traducciones",
  "header.nav.home.community.items.contribute": "Contribuir",

  "header.nav.taxonomy.label": "Cambio",
  "header.nav.taxonomy.circularity.title": "CIRCULARIDAD",
  "header.nav.taxonomy.circularity.items.available_surpluses": "Excedentes Disponibles",
  "header.nav.taxonomy.circularity.items.reuse_cases": "Casos de Reutilización",
  "header.nav.taxonomy.circularity.items.featured_materials": "Materiales Destacados",
  "header.nav.taxonomy.circularity.items.impact_indicators": "Indicadores de Impacto",
  "header.nav.taxonomy.reports.title": "DENUNCIAS",
  "header.nav.taxonomy.reports.items.reports_map": "Mapa de Denuncias",
  "header.nav.taxonomy.reports.items.categories": "Categorías",
  "header.nav.taxonomy.reports.items.official_guidelines": "Directrices Oficiales",
  "header.nav.taxonomy.reports.items.regional_stats": "Estadísticas Regionales",
  "header.nav.taxonomy.esg.title": "ESG & EMPRESAS",
  "header.nav.taxonomy.esg.items.mirr_reports": "Informes MIRR",
  "header.nav.taxonomy.esg.items.green_certs": "Certificaciones Verdes",
  "header.nav.taxonomy.esg.items.success_cases": "Casos de Éxito",
  "header.nav.taxonomy.esg.items.circular_partnerships": "Alianzas Circulares",
  "header.nav.taxonomy.cta_block.badge": "EMPEZAR",
  "header.nav.taxonomy.cta_block.title": "AHORA",
  "header.nav.taxonomy.cta_block.description": "Explorar, denunciar, compartir y reutilizar.",
  "header.nav.taxonomy.cta_block.button": "UNIRME",
  "header.nav.taxonomy.cta_block.alt": "P7CO CTA",

  "header.nav.blog.label": "Blog",
  "header.nav.blog.explore.title": "Explorar",
  "header.nav.blog.explore.items.all_posts": "Todos los artículos",
  "header.nav.blog.explore.items.featured": "Destacados",
  "header.nav.blog.explore.items.most_read": "Más leídos",
  "header.nav.blog.explore.items.authors": "Autores",
  "header.nav.blog.categories.title": "Categorías",
  "header.nav.blog.categories.items.guides": "Guías",
  "header.nav.blog.categories.items.news": "Noticias",
  "header.nav.blog.categories.items.case_studies": "Casos de Estudio",
  "header.nav.blog.categories.items.esg": "ESG",
  "header.nav.blog.categories.items.tech": "Tecnología",
  "header.nav.blog.languages.title": "Idiomas",
  "header.nav.blog.languages.items.pt": "Portugués",
  "header.nav.blog.languages.items.en": "Inglés",
  "header.nav.blog.languages.items.es": "Español",
  "header.nav.blog.languages.items.fr": "Francés",
  "header.nav.blog.languages.items.de": "Alemán",

  "header.nav.pages.label": "Acerca",
  "header.nav.pages.about.title": "Sobre",
  "header.nav.pages.about.items.about_us": "Sobre Nosotros",
  "header.nav.pages.about.items.team": "Equipo",
  "header.nav.pages.about.items.careers": "Carreras",
  "header.nav.pages.contacts.title": "Contactos",
  "header.nav.pages.contacts.items.contacts": "Contactos",
  "header.nav.pages.contacts.items.support": "Soporte",
  "header.nav.pages.faq.title": "FAQ",
  "header.nav.pages.faq.items.general_faq": "FAQ General",
  "header.nav.pages.faq.items.terms": "Términos de Uso",
  "header.nav.pages.faq.items.privacy": "Política de Privacidad",
  "header.nav.pages.faq.items.cookies": "Cookies",
  "header.nav.pages.faq.items.acknowledgements": "Agradecimientos",

  "header.nav.right.complaints": "Denuncias Ambientales",
  "header.nav.right.surpluses": "Excedentes",

  "header.auth.guest_menu_label": "Iniciar sesión",
  "header.auth.login": "Login",
  "header.auth.login_aria": "Iniciar sesión",
  "header.auth.create_account": "Crear Cuenta",
  "header.auth.user_menu_label": "Hola, {name}",
  "header.auth.dashboard": "Panel",
  "header.auth.my_listings": "Mis Listados",
  "header.auth.settings": "Configuraciones",
  "header.auth.logout": "Cerrar sesión",
  "header.auth.profile": "Ver Perfil",
  "header.auth.change_password": "Cambiar Contraseña",
  "header.auth.account_menu_aria": "Cuenta",
  "header.auth.account_fallback": "Cuenta",

  "header.cta_primary.text": "EMPEZAR",
  "header.cta_primary.icon": "fa-seedling",

  "header.nav.in.label": "Indicadores",
  "header.nav.in.explore.items.gee": "Emisiones GEI (PT)",
  "header.nav.in.categories.items.c27a": "CircularidadUE27 (año actual)",
  "header.nav.in.categories.items.c27": "CircularidadUE27 (vista técnica)"
}
