{
  "kicker": "UNTERNEHMENS- & KOMMUNALER IMPACT — EU27",
  "rotator.0": "unterstützt.",
  "rotator.1": "vernetzt.",
  "rotator.2": "skaliert.",
  "lead1": "P7CO® agiert im europäischen Kontext und hilft Gemeinden und Unternehmen, die Ziele der Europäischen Union für Kreislaufwirtschaft und Klimaneutralität zu erfüllen. Wir arbeiten im Einklang mit den Umweltpolitiken des EU-Raums und stärken Wettbewerbsfähigkeit sowie Zugang zu EU-Finanzierungen.",
  "lead2": "Durch die Integration EU-weit üblicher Praktiken fördern wir replizierbare, vergleichbare und auditierbare Lösungen. So können lokale wie multinationale Partner die EU-Anforderungen an Umwelt- und ESG-Berichte erfüllen und Glaubwürdigkeit bei Bürgern, Aufsichtsbehörden und Investoren gewinnen.",
  "cta.more_about": "EU27-Impact erkunden",
  "cta.more_about.aria": "Impact und Zonen in der EU27 erkunden",
  "img.partner.alt": "Partner und Gemeinden, die in der EU27 zusammenarbeiten"
}
